mkdocs_addresses/__init__.py
mkdocs_addresses/__version__.py
mkdocs_addresses/_test_data_extraction.py
mkdocs_addresses/addresses_checker.py
mkdocs_addresses/addresses_plugin.py
mkdocs_addresses/auto_completion_handler/__init__.py
mkdocs_addresses/auto_completion_handler/_base_handler.py
mkdocs_addresses/auto_completion_handler/_no_completion_handler.py
mkdocs_addresses/auto_completion_handler/_vsc_handlers.py
mkdocs_addresses/config_plugin.py
mkdocs_addresses/exceptions.py
mkdocs_addresses/logger.py
mkdocs_addresses/other_plugins_handling/__init__.py
mkdocs_addresses/other_plugins_handling/autorefs.py
mkdocs_addresses/path_manager.py
mkdocs_addresses/soup_excluding_codes.py
mkdocs_addresses/static_handler/__init__.py
mkdocs_addresses/static_handler/files_tracker.py
mkdocs_addresses/static_handler/static_handler.py
mkdocs_addresses/static_handler/tracker_addresses_usage_pool.py
mkdocs_addresses/static_handler/tracker_data_pages.py
mkdocs_addresses/static_handler/tracker_errors_counter.py
mkdocs_addresses/static_handler/tracker_references.py
mkdocs_addresses/static_handler/types_aliases.py
mkdocs_addresses/toolbox.py
mkdocs_addresses-0.5.6.dist-info/METADATA
mkdocs_addresses-0.5.6.dist-info/WHEEL
mkdocs_addresses-0.5.6.dist-info/entry_points.txt
mkdocs_addresses-0.5.6.dist-info/licenses/LICENSE.md
mkdocs_addresses-0.5.6.dist-info/RECORD
