Metadata-Version: 2.4
Name: mkdocs-addresses
Version: 0.5.6
Summary: Mkdocs automatic paths/addresses building - auto-completion support (VSC)
License: free-BSD
License-File: LICENSE.md
Keywords: mkdocs,mkdocs-plugin,links,autocompletion
Author: Frédéric Zinelli
Author-email: frederic.zinelli@gmail.com
Requires-Python: >=3.8, <4.0
Classifier: Environment :: Plugins
Classifier: Intended Audience :: Developers
Classifier: License :: OSI Approved :: Apache Software License
Classifier: Programming Language :: Python
Classifier: Programming Language :: Python :: 3.8
Classifier: Programming Language :: Python :: 3.9
Classifier: Programming Language :: Python :: 3.10
Classifier: Programming Language :: Python :: 3.11
Classifier: Operating System :: Microsoft :: Windows
Classifier: Operating System :: POSIX :: Linux
Classifier: Topic :: Documentation
Classifier: Topic :: Software Development
Classifier: Topic :: Software Development :: Documentation
Classifier: Topic :: Utilities
Requires-Dist: beautifulsoup4 (>=4.13.4,<5.0.0)
Requires-Dist: mkdocs (>=1.6)
Requires-Dist: mkdocs-material (>=9.5)
